surf_scrap/__init__.py
surf_scrap/scraper.py
surf_scrap-0.0.2.dist-info/METADATA
surf_scrap-0.0.2.dist-info/WHEEL
surf_scrap-0.0.2.dist-info/top_level.txt
surf_scrap-0.0.2.dist-info/RECORD
