Metadata-Version: 2.4
Name: surf_scrap
Version: 0.0.2
Summary: Une bibliothèque pour scraper les données de surf-report.com
Author: Rene, Cybelle
Requires-Python: >=3.7
Requires-Dist: requests
Requires-Dist: beautifulsoup4
Requires-Dist: pandas
